hollerith/__init__.py
hollerith/_version.py
hollerith/_writer.cp312-win_amd64.pyd
hollerith/field.py
hollerith/table.py
hollerith-0.6.0.dist-info/LICENSE
hollerith-0.6.0.dist-info/METADATA
hollerith-0.6.0.dist-info/WHEEL
hollerith-0.6.0.dist-info/top_level.txt
hollerith-0.6.0.dist-info/RECORD
