Metadata-Version: 2.1
Name: hollerith
Version: 0.6.0
Summary: C-extension module for efficient writing of fixed width text
Home-page: https://github.com/ansys/hollerith/
License: MIT
Project-URL: Documentation, https://hollerith.docs.pyansys.com/
Project-URL: Source, https://github.com/ansys/hollerith/
Project-URL: Tracker, https://github.com/ansys/hollerith/issues
Classifier: Development Status :: 4 - Beta
Classifier: Intended Audience :: Science/Research
Classifier: Topic :: Scientific/Engineering :: Information Analysis
Classifier: License :: OSI Approved :: MIT License
Classifier: Operating System :: Microsoft :: Windows
Classifier: Operating System :: POSIX
Classifier: Operating System :: MacOS
Classifier: Programming Language :: Python :: 3.10
Classifier: Programming Language :: Python :: 3.11
Classifier: Programming Language :: Python :: 3.12
Requires-Python: >=3.9
License-File: LICENSE
Requires-Dist: numpy>=1.26.4
Requires-Dist: pandas>=2.0.3
